dogceo/__init__.py
dogceo/dogapi.py
dogceo-1.0.0.dist-info/LICENSE
dogceo-1.0.0.dist-info/METADATA
dogceo-1.0.0.dist-info/WHEEL
dogceo-1.0.0.dist-info/top_level.txt
dogceo-1.0.0.dist-info/RECORD
