Metadata-Version: 2.1
Name: dogceo
Version: 1.0.0
Summary: Dog API client
Home-page: https://github.com/thexxiv/dogapi-py
Author: XXIV
License: UNKNOWN
Project-URL: Bug Tracker, https://github.com/thexxiv/dogapi-py/issues
Platform: UNKNOWN
Classifier: Programming Language :: Python :: 3
Classifier: License :: OSI Approved :: Apache Software License
Classifier: Operating System :: OS Independent
Requires-Python: >=3.6
License-File: LICENSE
